{
  "op_count": 100,
  "covered_op_count": 100,
  "expected_event_op_indices": [
    1,
    2,
    3,
    4,
    5,
    6,
    7,
    8,
    9,
    10,
    11,
    12,
    13,
    14,
    15,
    16,
    17,
    18,
    19,
    20,
    21,
    22,
    23,
    24,
    25,
    26,
    27,
    28,
    29,
    30,
    31,
    32,
    33,
    34,
    35,
    36,
    37,
    38,
    39,
    40,
    41,
    42,
    43,
    44,
    45,
    46,
    47,
    48,
    49,
    50,
    51,
    52,
    53,
    54,
    55,
    56,
    57,
    58,
    59,
    60,
    61,
    62,
    63,
    64,
    65,
    66,
    67,
    68,
    69,
    70,
    71,
    72,
    73,
    74,
    75,
    76,
    77,
    78,
    79,
    80,
    81,
    82,
    83,
    84,
    85,
    86,
    87,
    88,
    89,
    90,
    91,
    92,
    93,
    94,
    95,
    96,
    97,
    98,
    99,
    100
  ],
  "covered_event_op_indices": [
    1,
    2,
    3,
    4,
    5,
    6,
    7,
    8,
    9,
    10,
    11,
    12,
    13,
    14,
    15,
    16,
    17,
    18,
    19,
    20,
    21,
    22,
    23,
    24,
    25,
    26,
    27,
    28,
    29,
    30,
    31,
    32,
    33,
    34,
    35,
    36,
    37,
    38,
    39,
    40,
    41,
    42,
    43,
    44,
    45,
    46,
    47,
    48,
    49,
    50,
    51,
    52,
    53,
    54,
    55,
    56,
    57,
    58,
    59,
    60,
    61,
    62,
    63,
    64,
    65,
    66,
    67,
    68,
    69,
    70,
    71,
    72,
    73,
    74,
    75,
    76,
    77,
    78,
    79,
    80,
    81,
    82,
    83,
    84,
    85,
    86,
    87,
    88,
    89,
    90,
    91,
    92,
    93,
    94,
    95,
    96,
    97,
    98,
    99,
    100
  ],
  "covered_once_event_op_indices": [
    1,
    2,
    3,
    4,
    5,
    6,
    7,
    8,
    9,
    10,
    11,
    12,
    13,
    14,
    15,
    16,
    17,
    18,
    19,
    20,
    21,
    22,
    23,
    24,
    25,
    26,
    27,
    28,
    29,
    30,
    31,
    32,
    33,
    34,
    35,
    36,
    37,
    38,
    39,
    40,
    41,
    42,
    43,
    44,
    45,
    46,
    47,
    48,
    49,
    50,
    51,
    52,
    53,
    54,
    55,
    56,
    57,
    58,
    59,
    60,
    61,
    62,
    63,
    64,
    65,
    66,
    67,
    68,
    69,
    70,
    71,
    72,
    73,
    74,
    75,
    76,
    77,
    78,
    79,
    80,
    81,
    82,
    83,
    84,
    85,
    86,
    87,
    88,
    89,
    90,
    91,
    92,
    93,
    94,
    95,
    96,
    97,
    98,
    99,
    100
  ],
  "missing_event_op_indices": [],
  "duplicate_event_op_indices": [],
  "missing_from_module_split": [],
  "duplicate_module_split_indices": [],
  "missing_from_tensor_dataflow": [],
  "ops": [
    {
      "event_detail_id": "input1_layer22/input_layernorm/call0254/op0001",
      "event_op_index": 1,
      "global_op_index": 1721,
      "op_name": "to.dtype",
      "op_schema": "aten::to.dtype(Tensor(a) self, ScalarType dtype, bool non_blocking=False, bool copy=False, MemoryFormat? memory_format=None) -> Tensor(a)",
      "module_path": "model.layers.22.input_layernorm",
      "module_relative_path": "input_layernorm",
      "runtime_subprocess": "model.layers.22.input_layernorm",
      "module_split_covered": true,
      "tensor_dataflow_covered": true,
      "stage_evidence": [
        "input_rmsnorm"
      ],
      "input_tensor_ids": [
        "t00001761"
      ],
      "output_tensor_ids": [
        "t00001762"
      ]
    },
    {
      "event_detail_id": "input1_layer22/input_layernorm/call0254/op0002",
      "event_op_index": 2,
      "global_op_index": 1722,
      "op_name": "pow.Tensor_Scalar",
      "op_schema": "aten::pow.Tensor_Scalar(Tensor self, Scalar exponent) -> Tensor",
      "module_path": "model.layers.22.input_layernorm",
      "module_relative_path": "input_layernorm",
      "runtime_subprocess": "model.layers.22.input_layernorm",
      "module_split_covered": true,
      "tensor_dataflow_covered": true,
      "stage_evidence": [
        "input_rmsnorm"
      ],
      "input_tensor_ids": [
        "t00001762"
      ],
      "output_tensor_ids": [
        "t00001763"
      ]
    },
    {
      "event_detail_id": "input1_layer22/input_layernorm/call0254/op0003",
      "event_op_index": 3,
      "global_op_index": 1723,
      "op_name": "mean.dim",
      "op_schema": "aten::mean.dim(Tensor self, int[1]? dim, bool keepdim=False, *, ScalarType? dtype=None) -> Tensor",
      "module_path": "model.layers.22.input_layernorm",
      "module_relative_path": "input_layernorm",
      "runtime_subprocess": "model.layers.22.input_layernorm",
      "module_split_covered": true,
      "tensor_dataflow_covered": true,
      "stage_evidence": [
        "input_rmsnorm"
      ],
      "input_tensor_ids": [
        "t00001763"
      ],
      "output_tensor_ids": [
        "t00001764"
      ]
    },
    {
      "event_detail_id": "input1_layer22/input_layernorm/call0254/op0004",
      "event_op_index": 4,
      "global_op_index": 1724,
      "op_name": "add.Tensor",
      "op_schema": "aten::add.Tensor(Tensor self, Tensor other, *, Scalar alpha=1) -> Tensor",
      "module_path": "model.layers.22.input_layernorm",
      "module_relative_path": "input_layernorm",
      "runtime_subprocess": "model.layers.22.input_layernorm",
      "module_split_covered": true,
      "tensor_dataflow_covered": true,
      "stage_evidence": [
        "input_rmsnorm"
      ],
      "input_tensor_ids": [
        "t00001764"
      ],
      "output_tensor_ids": [
        "t00001765"
      ]
    },
    {
      "event_detail_id": "input1_layer22/input_layernorm/call0254/op0005",
      "event_op_index": 5,
      "global_op_index": 1725,
      "op_name": "rsqrt.default",
      "op_schema": "aten::rsqrt(Tensor self) -> Tensor",
      "module_path": "model.layers.22.input_layernorm",
      "module_relative_path": "input_layernorm",
      "runtime_subprocess": "model.layers.22.input_layernorm",
      "module_split_covered": true,
      "tensor_dataflow_covered": true,
      "stage_evidence": [
        "input_rmsnorm"
      ],
      "input_tensor_ids": [
        "t00001765"
      ],
      "output_tensor_ids": [
        "t00001766"
      ]
    },
    {
      "event_detail_id": "input1_layer22/input_layernorm/call0254/op0006",
      "event_op_index": 6,
      "global_op_index": 1726,
      "op_name": "mul.Tensor",
      "op_schema": "aten::mul.Tensor(Tensor self, Tensor other) -> Tensor",
      "module_path": "model.layers.22.input_layernorm",
      "module_relative_path": "input_layernorm",
      "runtime_subprocess": "model.layers.22.input_layernorm",
      "module_split_covered": true,
      "tensor_dataflow_covered": true,
      "stage_evidence": [
        "input_rmsnorm"
      ],
      "input_tensor_ids": [
        "t00001762",
        "t00001766"
      ],
      "output_tensor_ids": [
        "t00001767"
      ]
    },
    {
      "event_detail_id": "input1_layer22/input_layernorm/call0254/op0007",
      "event_op_index": 7,
      "global_op_index": 1727,
      "op_name": "to.dtype",
      "op_schema": "aten::to.dtype(Tensor(a) self, ScalarType dtype, bool non_blocking=False, bool copy=False, MemoryFormat? memory_format=None) -> Tensor(a)",
      "module_path": "model.layers.22.input_layernorm",
      "module_relative_path": "input_layernorm",
      "runtime_subprocess": "model.layers.22.input_layernorm",
      "module_split_covered": true,
      "tensor_dataflow_covered": true,
      "stage_evidence": [
        "input_rmsnorm"
      ],
      "input_tensor_ids": [
        "t00001767"
      ],
      "output_tensor_ids": [
        "t00001768"
      ]
    },
    {
      "event_detail_id": "input1_layer22/input_layernorm/call0254/op0008",
      "event_op_index": 8,
      "global_op_index": 1728,
      "op_name": "mul.Tensor",
      "op_schema": "aten::mul.Tensor(Tensor self, Tensor other) -> Tensor",
      "module_path": "model.layers.22.input_layernorm",
      "module_relative_path": "input_layernorm",
      "runtime_subprocess": "model.layers.22.input_layernorm",
      "module_split_covered": true,
      "tensor_dataflow_covered": true,
      "stage_evidence": [
        "input_rmsnorm"
      ],
      "input_tensor_ids": [
        "t00001769",
        "t00001768"
      ],
      "output_tensor_ids": [
        "t00001770"
      ]
    },
    {
      "event_detail_id": "input1_layer22/self_attn/q_proj/call0256/op0001",
      "event_op_index": 9,
      "global_op_index": 1729,
      "op_name": "linear.default",
      "op_schema": "aten::linear(Tensor input, Tensor weight, Tensor? bias=None) -> Tensor",
      "module_path": "model.layers.22.self_attn.q_proj",
      "module_relative_path": "self_attn.q_proj",
      "runtime_subprocess": "model.layers.22.self_attn.q_proj",
      "module_split_covered": true,
      "tensor_dataflow_covered": true,
      "stage_evidence": [
        "qkv_projection"
      ],
      "input_tensor_ids": [
        "t00001770",
        "t00001771"
      ],
      "output_tensor_ids": [
        "t00001772"
      ]
    },
    {
      "event_detail_id": "input1_layer22/self_attn/k_proj/call0257/op0001",
      "event_op_index": 10,
      "global_op_index": 1730,
      "op_name": "linear.default",
      "op_schema": "aten::linear(Tensor input, Tensor weight, Tensor? bias=None) -> Tensor",
      "module_path": "model.layers.22.self_attn.k_proj",
      "module_relative_path": "self_attn.k_proj",
      "runtime_subprocess": "model.layers.22.self_attn.k_proj",
      "module_split_covered": true,
      "tensor_dataflow_covered": true,
      "stage_evidence": [
        "qkv_projection"
      ],
      "input_tensor_ids": [
        "t00001770",
        "t00001773"
      ],
      "output_tensor_ids": [
        "t00001774"
      ]
    },
    {
      "event_detail_id": "input1_layer22/self_attn/v_proj/call0258/op0001",
      "event_op_index": 11,
      "global_op_index": 1731,
      "op_name": "linear.default",
      "op_schema": "aten::linear(Tensor input, Tensor weight, Tensor? bias=None) -> Tensor",
      "module_path": "model.layers.22.self_attn.v_proj",
      "module_relative_path": "self_attn.v_proj",
      "runtime_subprocess": "model.layers.22.self_attn.v_proj",
      "module_split_covered": true,
      "tensor_dataflow_covered": true,
      "stage_evidence": [
        "qkv_projection"
      ],
      "input_tensor_ids": [
        "t00001770",
        "t00001775"
      ],
      "output_tensor_ids": [
        "t00001776"
      ]
    },
    {
      "event_detail_id": "input1_layer22/self_attn/call0255/op0001",
      "event_op_index": 12,
      "global_op_index": 1732,
      "op_name": "view.default",
      "op_schema": "aten::view(Tensor(a) self, SymInt[] size) -> Tensor(a)",
      "module_path": "model.layers.22.self_attn",
      "module_relative_path": "self_attn",
      "runtime_subprocess": "model.layers.22.self_attn",
      "module_split_covered": true,
      "tensor_dataflow_covered": true,
      "stage_evidence": [
        "qkv_projection"
      ],
      "input_tensor_ids": [
        "t00001772"
      ],
      "output_tensor_ids": [
        "t00001777"
      ]
    },
    {
      "event_detail_id": "input1_layer22/self_attn/call0255/op0002",
      "event_op_index": 13,
      "global_op_index": 1733,
      "op_name": "transpose.int",
      "op_schema": "aten::transpose.int(Tensor(a) self, int dim0, int dim1) -> Tensor(a)",
      "module_path": "model.layers.22.self_attn",
      "module_relative_path": "self_attn",
      "runtime_subprocess": "model.layers.22.self_attn",
      "module_split_covered": true,
      "tensor_dataflow_covered": true,
      "stage_evidence": [
        "qkv_projection",
        "attention"
      ],
      "input_tensor_ids": [
        "t00001777"
      ],
      "output_tensor_ids": [
        "t00001778"
      ]
    },
    {
      "event_detail_id": "input1_layer22/self_attn/call0255/op0003",
      "event_op_index": 14,
      "global_op_index": 1734,
      "op_name": "view.default",
      "op_schema": "aten::view(Tensor(a) self, SymInt[] size) -> Tensor(a)",
      "module_path": "model.layers.22.self_attn",
      "module_relative_path": "self_attn",
      "runtime_subprocess": "model.layers.22.self_attn",
      "module_split_covered": true,
      "tensor_dataflow_covered": true,
      "stage_evidence": [
        "qkv_projection"
      ],
      "input_tensor_ids": [
        "t00001774"
      ],
      "output_tensor_ids": [
        "t00001779"
      ]
    },
    {
      "event_detail_id": "input1_layer22/self_attn/call0255/op0004",
      "event_op_index": 15,
      "global_op_index": 1735,
      "op_name": "transpose.int",
      "op_schema": "aten::transpose.int(Tensor(a) self, int dim0, int dim1) -> Tensor(a)",
      "module_path": "model.layers.22.self_attn",
      "module_relative_path": "self_attn",
      "runtime_subprocess": "model.layers.22.self_attn",
      "module_split_covered": true,
      "tensor_dataflow_covered": true,
      "stage_evidence": [
        "qkv_projection",
        "attention"
      ],
      "input_tensor_ids": [
        "t00001779"
      ],
      "output_tensor_ids": [
        "t00001780"
      ]
    },
    {
      "event_detail_id": "input1_layer22/self_attn/call0255/op0005",
      "event_op_index": 16,
      "global_op_index": 1736,
      "op_name": "view.default",
      "op_schema": "aten::view(Tensor(a) self, SymInt[] size) -> Tensor(a)",
      "module_path": "model.layers.22.self_attn",
      "module_relative_path": "self_attn",
      "runtime_subprocess": "model.layers.22.self_attn",
      "module_split_covered": true,
      "tensor_dataflow_covered": true,
      "stage_evidence": [
        "qkv_projection"
      ],
      "input_tensor_ids": [
        "t00001776"
      ],
      "output_tensor_ids": [
        "t00001781"
      ]
    },
    {
      "event_detail_id": "input1_layer22/self_attn/call0255/op0006",
      "event_op_index": 17,
      "global_op_index": 1737,
      "op_name": "transpose.int",
      "op_schema": "aten::transpose.int(Tensor(a) self, int dim0, int dim1) -> Tensor(a)",
      "module_path": "model.layers.22.self_attn",
      "module_relative_path": "self_attn",
      "runtime_subprocess": "model.layers.22.self_attn",
      "module_split_covered": true,
      "tensor_dataflow_covered": true,
      "stage_evidence": [
        "qkv_projection",
        "attention"
      ],
      "input_tensor_ids": [
        "t00001781"
      ],
      "output_tensor_ids": [
        "t00001782"
      ]
    },
    {
      "event_detail_id": "input1_layer22/self_attn/call0255/op0007",
      "event_op_index": 18,
      "global_op_index": 1738,
      "op_name": "select.int",
      "op_schema": "aten::select.int(Tensor(a) self, int dim, SymInt index) -> Tensor(a)",
      "module_path": "model.layers.22.self_attn",
      "module_relative_path": "self_attn",
      "runtime_subprocess": "model.layers.22.self_attn",
      "module_split_covered": true,
      "tensor_dataflow_covered": true,
      "stage_evidence": [],
      "input_tensor_ids": [
        "t00001475"
      ],
      "output_tensor_ids": [
        "t00001783"
      ]
    },
    {
      "event_detail_id": "input1_layer22/self_attn/call0255/op0008",
      "event_op_index": 19,
      "global_op_index": 1739,
      "op_name": "select.int",
      "op_schema": "aten::select.int(Tensor(a) self, int dim, SymInt index) -> Tensor(a)",
      "module_path": "model.layers.22.self_attn",
      "module_relative_path": "self_attn",
      "runtime_subprocess": "model.layers.22.self_attn",
      "module_split_covered": true,
      "tensor_dataflow_covered": true,
      "stage_evidence": [],
      "input_tensor_ids": [
        "t00001783"
      ],
      "output_tensor_ids": [
        "t00001784"
      ]
    },
    {
      "event_detail_id": "input1_layer22/self_attn/call0255/op0009",
      "event_op_index": 20,
      "global_op_index": 1740,
      "op_name": "add.Tensor",
      "op_schema": "aten::add.Tensor(Tensor self, Tensor other, *, Scalar alpha=1) -> Tensor",
      "module_path": "model.layers.22.self_attn",
      "module_relative_path": "self_attn",
      "runtime_subprocess": "model.layers.22.self_attn",
      "module_split_covered": true,
      "tensor_dataflow_covered": true,
      "stage_evidence": [
        "rope"
      ],
      "input_tensor_ids": [
        "t00001784"
      ],
      "output_tensor_ids": [
        "t00001785"
      ]
    },
    {
      "event_detail_id": "input1_layer22/self_attn/rotary_emb/call0259/op0001",
      "event_op_index": 21,
      "global_op_index": 1741,
      "op_name": "gt.Scalar",
      "op_schema": "aten::gt.Scalar(Tensor self, Scalar other) -> Tensor",
      "module_path": "model.layers.22.self_attn.rotary_emb",
      "module_relative_path": "self_attn.rotary_emb",
      "runtime_subprocess": "model.layers.22.self_attn.rotary_emb",
      "module_split_covered": true,
      "tensor_dataflow_covered": true,
      "stage_evidence": [
        "visipruner_similarity_check"
      ],
      "input_tensor_ids": [
        "t00001785"
      ],
      "output_tensor_ids": [
        "t00001786"
      ]
    },
    {
      "event_detail_id": "input1_layer22/self_attn/rotary_emb/call0259/op0002",
      "event_op_index": 22,
      "global_op_index": 1742,
      "op_name": "is_nonzero.default",
      "op_schema": "aten::is_nonzero(Tensor self) -> bool",
      "module_path": "model.layers.22.self_attn.rotary_emb",
      "module_relative_path": "self_attn.rotary_emb",
      "runtime_subprocess": "model.layers.22.self_attn.rotary_emb",
      "module_split_covered": true,
      "tensor_dataflow_covered": true,
      "stage_evidence": [
        "visipruner_similarity_check"
      ],
      "input_tensor_ids": [
        "t00001786"
      ],
      "output_tensor_ids": []
    },
    {
      "event_detail_id": "input1_layer22/self_attn/rotary_emb/call0259/op0003",
      "event_op_index": 23,
      "global_op_index": 1743,
      "op_name": "item.default",
      "op_schema": "aten::item(Tensor self) -> Scalar",
      "module_path": "model.layers.22.self_attn.rotary_emb",
      "module_relative_path": "self_attn.rotary_emb",
      "runtime_subprocess": "model.layers.22.self_attn.rotary_emb",
      "module_split_covered": true,
      "tensor_dataflow_covered": true,
      "stage_evidence": [],
      "input_tensor_ids": [
        "t00001785"
      ],
      "output_tensor_ids": []
    },
    {
      "event_detail_id": "input1_layer22/self_attn/rotary_emb/call0259/op0004",
      "event_op_index": 24,
      "global_op_index": 1744,
      "op_name": "slice.Tensor",
      "op_schema": "aten::slice.Tensor(Tensor(a) self, int dim=0, SymInt? start=None, SymInt? end=None, SymInt step=1) -> Tensor(a)",
      "module_path": "model.layers.22.self_attn.rotary_emb",
      "module_relative_path": "self_attn.rotary_emb",
      "runtime_subprocess": "model.layers.22.self_attn.rotary_emb",
      "module_split_covered": true,
      "tensor_dataflow_covered": true,
      "stage_evidence": [
        "rope"
      ],
      "input_tensor_ids": [
        "t00001787"
      ],
      "output_tensor_ids": [
        "t00001788"
      ]
    },
    {
      "event_detail_id": "input1_layer22/self_attn/rotary_emb/call0259/op0005",
      "event_op_index": 25,
      "global_op_index": 1745,
      "op_name": "to.dtype",
      "op_schema": "aten::to.dtype(Tensor(a) self, ScalarType dtype, bool non_blocking=False, bool copy=False, MemoryFormat? memory_format=None) -> Tensor(a)",
      "module_path": "model.layers.22.self_attn.rotary_emb",
      "module_relative_path": "self_attn.rotary_emb",
      "runtime_subprocess": "model.layers.22.self_attn.rotary_emb",
      "module_split_covered": true,
      "tensor_dataflow_covered": true,
      "stage_evidence": [],
      "input_tensor_ids": [
        "t00001788"
      ],
      "output_tensor_ids": [
        "t00001788"
      ]
    },
    {
      "event_detail_id": "input1_layer22/self_attn/rotary_emb/call0259/op0006",
      "event_op_index": 26,
      "global_op_index": 1746,
      "op_name": "item.default",
      "op_schema": "aten::item(Tensor self) -> Scalar",
      "module_path": "model.layers.22.self_attn.rotary_emb",
      "module_relative_path": "self_attn.rotary_emb",
      "runtime_subprocess": "model.layers.22.self_attn.rotary_emb",
      "module_split_covered": true,
      "tensor_dataflow_covered": true,
      "stage_evidence": [],
      "input_tensor_ids": [
        "t00001785"
      ],
      "output_tensor_ids": []
    },
    {
      "event_detail_id": "input1_layer22/self_attn/rotary_emb/call0259/op0007",
      "event_op_index": 27,
      "global_op_index": 1747,
      "op_name": "slice.Tensor",
      "op_schema": "aten::slice.Tensor(Tensor(a) self, int dim=0, SymInt? start=None, SymInt? end=None, SymInt step=1) -> Tensor(a)",
      "module_path": "model.layers.22.self_attn.rotary_emb",
      "module_relative_path": "self_attn.rotary_emb",
      "runtime_subprocess": "model.layers.22.self_attn.rotary_emb",
      "module_split_covered": true,
      "tensor_dataflow_covered": true,
      "stage_evidence": [
        "rope"
      ],
      "input_tensor_ids": [
        "t00001789"
      ],
      "output_tensor_ids": [
        "t00001790"
      ]
    },
    {
      "event_detail_id": "input1_layer22/self_attn/rotary_emb/call0259/op0008",
      "event_op_index": 28,
      "global_op_index": 1748,
      "op_name": "to.dtype",
      "op_schema": "aten::to.dtype(Tensor(a) self, ScalarType dtype, bool non_blocking=False, bool copy=False, MemoryFormat? memory_format=None) -> Tensor(a)",
      "module_path": "model.layers.22.self_attn.rotary_emb",
      "module_relative_path": "self_attn.rotary_emb",
      "runtime_subprocess": "model.layers.22.self_attn.rotary_emb",
      "module_split_covered": true,
      "tensor_dataflow_covered": true,
      "stage_evidence": [],
      "input_tensor_ids": [
        "t00001790"
      ],
      "output_tensor_ids": [
        "t00001790"
      ]
    },
    {
      "event_detail_id": "input1_layer22/self_attn/call0255/op0010",
      "event_op_index": 29,
      "global_op_index": 1749,
      "op_name": "index.Tensor",
      "op_schema": "aten::index.Tensor(Tensor self, Tensor?[] indices) -> Tensor",
      "module_path": "model.layers.22.self_attn",
      "module_relative_path": "self_attn",
      "runtime_subprocess": "model.layers.22.self_attn",
      "module_split_covered": true,
      "tensor_dataflow_covered": true,
      "stage_evidence": [
        "rope"
      ],
      "input_tensor_ids": [
        "t00001788",
        "t00001475"
      ],
      "output_tensor_ids": [
        "t00001791"
      ]
    },
    {
      "event_detail_id": "input1_layer22/self_attn/call0255/op0011",
      "event_op_index": 30,
      "global_op_index": 1750,
      "op_name": "unsqueeze.default",
      "op_schema": "aten::unsqueeze(Tensor(a) self, int dim) -> Tensor(a)",
      "module_path": "model.layers.22.self_attn",
      "module_relative_path": "self_attn",
      "runtime_subprocess": "model.layers.22.self_attn",
      "module_split_covered": true,
      "tensor_dataflow_covered": true,
      "stage_evidence": [
        "rope"
      ],
      "input_tensor_ids": [
        "t00001791"
      ],
      "output_tensor_ids": [
        "t00001792"
      ]
    },
    {
      "event_detail_id": "input1_layer22/self_attn/call0255/op0012",
      "event_op_index": 31,
      "global_op_index": 1751,
      "op_name": "index.Tensor",
      "op_schema": "aten::index.Tensor(Tensor self, Tensor?[] indices) -> Tensor",
      "module_path": "model.layers.22.self_attn",
      "module_relative_path": "self_attn",
      "runtime_subprocess": "model.layers.22.self_attn",
      "module_split_covered": true,
      "tensor_dataflow_covered": true,
      "stage_evidence": [
        "rope"
      ],
      "input_tensor_ids": [
        "t00001790",
        "t00001475"
      ],
      "output_tensor_ids": [
        "t00001793"
      ]
    },
    {
      "event_detail_id": "input1_layer22/self_attn/call0255/op0013",
      "event_op_index": 32,
      "global_op_index": 1752,
      "op_name": "unsqueeze.default",
      "op_schema": "aten::unsqueeze(Tensor(a) self, int dim) -> Tensor(a)",
      "module_path": "model.layers.22.self_attn",
      "module_relative_path": "self_attn",
      "runtime_subprocess": "model.layers.22.self_attn",
      "module_split_covered": true,
      "tensor_dataflow_covered": true,
      "stage_evidence": [
        "rope"
      ],
      "input_tensor_ids": [
        "t00001793"
      ],
      "output_tensor_ids": [
        "t00001794"
      ]
    },
    {
      "event_detail_id": "input1_layer22/self_attn/call0255/op0014",
      "event_op_index": 33,
      "global_op_index": 1753,
      "op_name": "mul.Tensor",
      "op_schema": "aten::mul.Tensor(Tensor self, Tensor other) -> Tensor",
      "module_path": "model.layers.22.self_attn",
      "module_relative_path": "self_attn",
      "runtime_subprocess": "model.layers.22.self_attn",
      "module_split_covered": true,
      "tensor_dataflow_covered": true,
      "stage_evidence": [
        "rope"
      ],
      "input_tensor_ids": [
        "t00001778",
        "t00001792"
      ],
      "output_tensor_ids": [
        "t00001795"
      ]
    },
    {
      "event_detail_id": "input1_layer22/self_attn/call0255/op0015",
      "event_op_index": 34,
      "global_op_index": 1754,
      "op_name": "slice.Tensor",
      "op_schema": "aten::slice.Tensor(Tensor(a) self, int dim=0, SymInt? start=None, SymInt? end=None, SymInt step=1) -> Tensor(a)",
      "module_path": "model.layers.22.self_attn",
      "module_relative_path": "self_attn",
      "runtime_subprocess": "model.layers.22.self_attn",
      "module_split_covered": true,
      "tensor_dataflow_covered": true,
      "stage_evidence": [
        "rope"
      ],
      "input_tensor_ids": [
        "t00001778"
      ],
      "output_tensor_ids": [
        "t00001796"
      ]
    },
    {
      "event_detail_id": "input1_layer22/self_attn/call0255/op0016",
      "event_op_index": 35,
      "global_op_index": 1755,
      "op_name": "slice.Tensor",
      "op_schema": "aten::slice.Tensor(Tensor(a) self, int dim=0, SymInt? start=None, SymInt? end=None, SymInt step=1) -> Tensor(a)",
      "module_path": "model.layers.22.self_attn",
      "module_relative_path": "self_attn",
      "runtime_subprocess": "model.layers.22.self_attn",
      "module_split_covered": true,
      "tensor_dataflow_covered": true,
      "stage_evidence": [
        "rope"
      ],
      "input_tensor_ids": [
        "t00001778"
      ],
      "output_tensor_ids": [
        "t00001797"
      ]
    },
    {
      "event_detail_id": "input1_layer22/self_attn/call0255/op0017",
      "event_op_index": 36,
      "global_op_index": 1756,
      "op_name": "neg.default",
      "op_schema": "aten::neg(Tensor self) -> Tensor",
      "module_path": "model.layers.22.self_attn",
      "module_relative_path": "self_attn",
      "runtime_subprocess": "model.layers.22.self_attn",
      "module_split_covered": true,
      "tensor_dataflow_covered": true,
      "stage_evidence": [
        "rope"
      ],
      "input_tensor_ids": [
        "t00001797"
      ],
      "output_tensor_ids": [
        "t00001798"
      ]
    },
    {
      "event_detail_id": "input1_layer22/self_attn/call0255/op0018",
      "event_op_index": 37,
      "global_op_index": 1757,
      "op_name": "cat.default",
      "op_schema": "aten::cat(Tensor[] tensors, int dim=0) -> Tensor",
      "module_path": "model.layers.22.self_attn",
      "module_relative_path": "self_attn",
      "runtime_subprocess": "model.layers.22.self_attn",
      "module_split_covered": true,
      "tensor_dataflow_covered": true,
      "stage_evidence": [
        "rope"
      ],
      "input_tensor_ids": [
        "t00001798",
        "t00001796"
      ],
      "output_tensor_ids": [
        "t00001799"
      ]
    },
    {
      "event_detail_id": "input1_layer22/self_attn/call0255/op0019",
      "event_op_index": 38,
      "global_op_index": 1758,
      "op_name": "mul.Tensor",
      "op_schema": "aten::mul.Tensor(Tensor self, Tensor other) -> Tensor",
      "module_path": "model.layers.22.self_attn",
      "module_relative_path": "self_attn",
      "runtime_subprocess": "model.layers.22.self_attn",
      "module_split_covered": true,
      "tensor_dataflow_covered": true,
      "stage_evidence": [
        "rope"
      ],
      "input_tensor_ids": [
        "t00001799",
        "t00001794"
      ],
      "output_tensor_ids": [
        "t00001800"
      ]
    },
    {
      "event_detail_id": "input1_layer22/self_attn/call0255/op0020",
      "event_op_index": 39,
      "global_op_index": 1759,
      "op_name": "add.Tensor",
      "op_schema": "aten::add.Tensor(Tensor self, Tensor other, *, Scalar alpha=1) -> Tensor",
      "module_path": "model.layers.22.self_attn",
      "module_relative_path": "self_attn",
      "runtime_subprocess": "model.layers.22.self_attn",
      "module_split_covered": true,
      "tensor_dataflow_covered": true,
      "stage_evidence": [
        "rope",
        "attention"
      ],
      "input_tensor_ids": [
        "t00001795",
        "t00001800"
      ],
      "output_tensor_ids": [
        "t00001801"
      ]
    },
    {
      "event_detail_id": "input1_layer22/self_attn/call0255/op0021",
      "event_op_index": 40,
      "global_op_index": 1760,
      "op_name": "mul.Tensor",
      "op_schema": "aten::mul.Tensor(Tensor self, Tensor other) -> Tensor",
      "module_path": "model.layers.22.self_attn",
      "module_relative_path": "self_attn",
      "runtime_subprocess": "model.layers.22.self_attn",
      "module_split_covered": true,
      "tensor_dataflow_covered": true,
      "stage_evidence": [],
      "input_tensor_ids": [
        "t00001780",
        "t00001792"
      ],
      "output_tensor_ids": [
        "t00001802"
      ]
    },
    {
      "event_detail_id": "input1_layer22/self_attn/call0255/op0022",
      "event_op_index": 41,
      "global_op_index": 1761,
      "op_name": "slice.Tensor",
      "op_schema": "aten::slice.Tensor(Tensor(a) self, int dim=0, SymInt? start=None, SymInt? end=None, SymInt step=1) -> Tensor(a)",
      "module_path": "model.layers.22.self_attn",
      "module_relative_path": "self_attn",
      "runtime_subprocess": "model.layers.22.self_attn",
      "module_split_covered": true,
      "tensor_dataflow_covered": true,
      "stage_evidence": [],
      "input_tensor_ids": [
        "t00001780"
      ],
      "output_tensor_ids": [
        "t00001803"
      ]
    },
    {
      "event_detail_id": "input1_layer22/self_attn/call0255/op0023",
      "event_op_index": 42,
      "global_op_index": 1762,
      "op_name": "slice.Tensor",
      "op_schema": "aten::slice.Tensor(Tensor(a) self, int dim=0, SymInt? start=None, SymInt? end=None, SymInt step=1) -> Tensor(a)",
      "module_path": "model.layers.22.self_attn",
      "module_relative_path": "self_attn",
      "runtime_subprocess": "model.layers.22.self_attn",
      "module_split_covered": true,
      "tensor_dataflow_covered": true,
      "stage_evidence": [],
      "input_tensor_ids": [
        "t00001780"
      ],
      "output_tensor_ids": [
        "t00001804"
      ]
    },
    {
      "event_detail_id": "input1_layer22/self_attn/call0255/op0024",
      "event_op_index": 43,
      "global_op_index": 1763,
      "op_name": "neg.default",
      "op_schema": "aten::neg(Tensor self) -> Tensor",
      "module_path": "model.layers.22.self_attn",
      "module_relative_path": "self_attn",
      "runtime_subprocess": "model.layers.22.self_attn",
      "module_split_covered": true,
      "tensor_dataflow_covered": true,
      "stage_evidence": [],
      "input_tensor_ids": [
        "t00001804"
      ],
      "output_tensor_ids": [
        "t00001805"
      ]
    },
    {
      "event_detail_id": "input1_layer22/self_attn/call0255/op0025",
      "event_op_index": 44,
      "global_op_index": 1764,
      "op_name": "cat.default",
      "op_schema": "aten::cat(Tensor[] tensors, int dim=0) -> Tensor",
      "module_path": "model.layers.22.self_attn",
      "module_relative_path": "self_attn",
      "runtime_subprocess": "model.layers.22.self_attn",
      "module_split_covered": true,
      "tensor_dataflow_covered": true,
      "stage_evidence": [],
      "input_tensor_ids": [
        "t00001805",
        "t00001803"
      ],
      "output_tensor_ids": [
        "t00001806"
      ]
    },
    {
      "event_detail_id": "input1_layer22/self_attn/call0255/op0026",
      "event_op_index": 45,
      "global_op_index": 1765,
      "op_name": "mul.Tensor",
      "op_schema": "aten::mul.Tensor(Tensor self, Tensor other) -> Tensor",
      "module_path": "model.layers.22.self_attn",
      "module_relative_path": "self_attn",
      "runtime_subprocess": "model.layers.22.self_attn",
      "module_split_covered": true,
      "tensor_dataflow_covered": true,
      "stage_evidence": [],
      "input_tensor_ids": [
        "t00001806",
        "t00001794"
      ],
      "output_tensor_ids": [
        "t00001807"
      ]
    },
    {
      "event_detail_id": "input1_layer22/self_attn/call0255/op0027",
      "event_op_index": 46,
      "global_op_index": 1766,
      "op_name": "add.Tensor",
      "op_schema": "aten::add.Tensor(Tensor self, Tensor other, *, Scalar alpha=1) -> Tensor",
      "module_path": "model.layers.22.self_attn",
      "module_relative_path": "self_attn",
      "runtime_subprocess": "model.layers.22.self_attn",
      "module_split_covered": true,
      "tensor_dataflow_covered": true,
      "stage_evidence": [
        "attention"
      ],
      "input_tensor_ids": [
        "t00001802",
        "t00001807"
      ],
      "output_tensor_ids": [
        "t00001808"
      ]
    },
    {
      "event_detail_id": "input1_layer22/self_attn/call0255/op0028",
      "event_op_index": 47,
      "global_op_index": 1767,
      "op_name": "transpose.int",
      "op_schema": "aten::transpose.int(Tensor(a) self, int dim0, int dim1) -> Tensor(a)",
      "module_path": "model.layers.22.self_attn",
      "module_relative_path": "self_attn",
      "runtime_subprocess": "model.layers.22.self_attn",
      "module_split_covered": true,
      "tensor_dataflow_covered": true,
      "stage_evidence": [
        "attention"
      ],
      "input_tensor_ids": [
        "t00001808"
      ],
      "output_tensor_ids": [
        "t00001809"
      ]
    },
    {
      "event_detail_id": "input1_layer22/self_attn/call0255/op0029",
      "event_op_index": 48,
      "global_op_index": 1768,
      "op_name": "matmul.default",
      "op_schema": "aten::matmul(Tensor self, Tensor other) -> Tensor",
      "module_path": "model.layers.22.self_attn",
      "module_relative_path": "self_attn",
      "runtime_subprocess": "model.layers.22.self_attn",
      "module_split_covered": true,
      "tensor_dataflow_covered": true,
      "stage_evidence": [
        "attention"
      ],
      "input_tensor_ids": [
        "t00001801",
        "t00001809"
      ],
      "output_tensor_ids": [
        "t00001810"
      ]
    },
    {
      "event_detail_id": "input1_layer22/self_attn/call0255/op0030",
      "event_op_index": 49,
      "global_op_index": 1769,
      "op_name": "div.Tensor",
      "op_schema": "aten::div.Tensor(Tensor self, Tensor other) -> Tensor",
      "module_path": "model.layers.22.self_attn",
      "module_relative_path": "self_attn",
      "runtime_subprocess": "model.layers.22.self_attn",
      "module_split_covered": true,
      "tensor_dataflow_covered": true,
      "stage_evidence": [
        "attention"
      ],
      "input_tensor_ids": [
        "t00001810"
      ],
      "output_tensor_ids": [
        "t00001811"
      ]
    },
    {
      "event_detail_id": "input1_layer22/self_attn/call0255/op0031",
      "event_op_index": 50,
      "global_op_index": 1770,
      "op_name": "add.Tensor",
      "op_schema": "aten::add.Tensor(Tensor self, Tensor other, *, Scalar alpha=1) -> Tensor",
      "module_path": "model.layers.22.self_attn",
      "module_relative_path": "self_attn",
      "runtime_subprocess": "model.layers.22.self_attn",
      "module_split_covered": true,
      "tensor_dataflow_covered": true,
      "stage_evidence": [
        "attention"
      ],
      "input_tensor_ids": [
        "t00001811",
        "t00001505"
      ],
      "output_tensor_ids": [
        "t00001812"
      ]
    },
    {
      "event_detail_id": "input1_layer22/self_attn/call0255/op0032",
      "event_op_index": 51,
      "global_op_index": 1771,
      "op_name": "softmax.int",
      "op_schema": "aten::softmax.int(Tensor self, int dim, ScalarType? dtype=None) -> Tensor",
      "module_path": "model.layers.22.self_attn",
      "module_relative_path": "self_attn",
      "runtime_subprocess": "model.layers.22.self_attn",
      "module_split_covered": true,
      "tensor_dataflow_covered": true,
      "stage_evidence": [
        "attention"
      ],
      "input_tensor_ids": [
        "t00001812"
      ],
      "output_tensor_ids": [
        "t00001813"
      ]
    },
    {
      "event_detail_id": "input1_layer22/self_attn/call0255/op0033",
      "event_op_index": 52,
      "global_op_index": 1772,
      "op_name": "to.dtype",
      "op_schema": "aten::to.dtype(Tensor(a) self, ScalarType dtype, bool non_blocking=False, bool copy=False, MemoryFormat? memory_format=None) -> Tensor(a)",
      "module_path": "model.layers.22.self_attn",
      "module_relative_path": "self_attn",
      "runtime_subprocess": "model.layers.22.self_attn",
      "module_split_covered": true,
      "tensor_dataflow_covered": true,
      "stage_evidence": [],
      "input_tensor_ids": [
        "t00001813"
      ],
      "output_tensor_ids": [
        "t00001814"
      ]
    },
    {
      "event_detail_id": "input1_layer22/self_attn/call0255/op0034",
      "event_op_index": 53,
      "global_op_index": 1773,
      "op_name": "dropout.default",
      "op_schema": "aten::dropout(Tensor input, float p, bool train) -> Tensor",
      "module_path": "model.layers.22.self_attn",
      "module_relative_path": "self_attn",
      "runtime_subprocess": "model.layers.22.self_attn",
      "module_split_covered": true,
      "tensor_dataflow_covered": true,
      "stage_evidence": [
        "attention"
      ],
      "input_tensor_ids": [
        "t00001814"
      ],
      "output_tensor_ids": [
        "t00001814"
      ]
    },
    {
      "event_detail_id": "input1_layer22/self_attn/call0255/op0035",
      "event_op_index": 54,
      "global_op_index": 1774,
      "op_name": "matmul.default",
      "op_schema": "aten::matmul(Tensor self, Tensor other) -> Tensor",
      "module_path": "model.layers.22.self_attn",
      "module_relative_path": "self_attn",
      "runtime_subprocess": "model.layers.22.self_attn",
      "module_split_covered": true,
      "tensor_dataflow_covered": true,
      "stage_evidence": [
        "attention",
        "attention_output"
      ],
      "input_tensor_ids": [
        "t00001814",
        "t00001782"
      ],
      "output_tensor_ids": [
        "t00001815"
      ]
    },
    {
      "event_detail_id": "input1_layer22/self_attn/call0255/op0036",
      "event_op_index": 55,
      "global_op_index": 1775,
      "op_name": "transpose.int",
      "op_schema": "aten::transpose.int(Tensor(a) self, int dim0, int dim1) -> Tensor(a)",
      "module_path": "model.layers.22.self_attn",
      "module_relative_path": "self_attn",
      "runtime_subprocess": "model.layers.22.self_attn",
      "module_split_covered": true,
      "tensor_dataflow_covered": true,
      "stage_evidence": [],
      "input_tensor_ids": [
        "t00001815"
      ],
      "output_tensor_ids": [
        "t00001816"
      ]
    },
    {
      "event_detail_id": "input1_layer22/self_attn/call0255/op0037",
      "event_op_index": 56,
      "global_op_index": 1776,
      "op_name": "contiguous.default",
      "op_schema": "aten::contiguous(Tensor(a) self, *, MemoryFormat memory_format=0) -> Tensor(a)",
      "module_path": "model.layers.22.self_attn",
      "module_relative_path": "self_attn",
      "runtime_subprocess": "model.layers.22.self_attn",
      "module_split_covered": true,
      "tensor_dataflow_covered": true,
      "stage_evidence": [
        "attention_output"
      ],
      "input_tensor_ids": [
        "t00001816"
      ],
      "output_tensor_ids": [
        "t00001817"
      ]
    },
    {
      "event_detail_id": "input1_layer22/self_attn/call0255/op0038",
      "event_op_index": 57,
      "global_op_index": 1777,
      "op_name": "reshape.default",
      "op_schema": "aten::reshape(Tensor(a) self, SymInt[] shape) -> Tensor(a)",
      "module_path": "model.layers.22.self_attn",
      "module_relative_path": "self_attn",
      "runtime_subprocess": "model.layers.22.self_attn",
      "module_split_covered": true,
      "tensor_dataflow_covered": true,
      "stage_evidence": [
        "attention_output"
      ],
      "input_tensor_ids": [
        "t00001817"
      ],
      "output_tensor_ids": [
        "t00001818"
      ]
    },
    {
      "event_detail_id": "input1_layer22/self_attn/call0255/op0039",
      "event_op_index": 58,
      "global_op_index": 1778,
      "op_name": "gt.Scalar",
      "op_schema": "aten::gt.Scalar(Tensor self, Scalar other) -> Tensor",
      "module_path": "model.layers.22.self_attn",
      "module_relative_path": "self_attn",
      "runtime_subprocess": "model.layers.22.self_attn",
      "module_split_covered": true,
      "tensor_dataflow_covered": true,
      "stage_evidence": [
        "visipruner_similarity_check"
      ],
      "input_tensor_ids": [
        "t00000057"
      ],
      "output_tensor_ids": [
        "t00001819"
      ]
    },
    {
      "event_detail_id": "input1_layer22/self_attn/call0255/op0040",
      "event_op_index": 59,
      "global_op_index": 1779,
      "op_name": "is_nonzero.default",
      "op_schema": "aten::is_nonzero(Tensor self) -> bool",
      "module_path": "model.layers.22.self_attn",
      "module_relative_path": "self_attn",
      "runtime_subprocess": "model.layers.22.self_attn",
      "module_split_covered": true,
      "tensor_dataflow_covered": true,
      "stage_evidence": [
        "visipruner_similarity_check"
      ],
      "input_tensor_ids": [
        "t00001819"
      ],
      "output_tensor_ids": []
    },
    {
      "event_detail_id": "input1_layer22/self_attn/call0255/op0041",
      "event_op_index": 60,
      "global_op_index": 1780,
      "op_name": "select.int",
      "op_schema": "aten::select.int(Tensor(a) self, int dim, SymInt index) -> Tensor(a)",
      "module_path": "model.layers.22.self_attn",
      "module_relative_path": "self_attn",
      "runtime_subprocess": "model.layers.22.self_attn",
      "module_split_covered": true,
      "tensor_dataflow_covered": true,
      "stage_evidence": [],
      "input_tensor_ids": [
        "t00001475"
      ],
      "output_tensor_ids": [
        "t00001820"
      ]
    },
    {
      "event_detail_id": "input1_layer22/self_attn/call0255/op0042",
      "event_op_index": 61,
      "global_op_index": 1781,
      "op_name": "select.int",
      "op_schema": "aten::select.int(Tensor(a) self, int dim, SymInt index) -> Tensor(a)",
      "module_path": "model.layers.22.self_attn",
      "module_relative_path": "self_attn",
      "runtime_subprocess": "model.layers.22.self_attn",
      "module_split_covered": true,
      "tensor_dataflow_covered": true,
      "stage_evidence": [],
      "input_tensor_ids": [
        "t00001820"
      ],
      "output_tensor_ids": [
        "t00001821"
      ]
    },
    {
      "event_detail_id": "input1_layer22/self_attn/call0255/op0043",
      "event_op_index": 62,
      "global_op_index": 1782,
      "op_name": "add.Tensor",
      "op_schema": "aten::add.Tensor(Tensor self, Tensor other, *, Scalar alpha=1) -> Tensor",
      "module_path": "model.layers.22.self_attn",
      "module_relative_path": "self_attn",
      "runtime_subprocess": "model.layers.22.self_attn",
      "module_split_covered": true,
      "tensor_dataflow_covered": true,
      "stage_evidence": [],
      "input_tensor_ids": [
        "t00001821"
      ],
      "output_tensor_ids": [
        "t00001822"
      ]
    },
    {
      "event_detail_id": "input1_layer22/self_attn/call0255/op0044",
      "event_op_index": 63,
      "global_op_index": 1783,
      "op_name": "mul.Tensor",
      "op_schema": "aten::mul.Tensor(Tensor self, Tensor other) -> Tensor",
      "module_path": "model.layers.22.self_attn",
      "module_relative_path": "self_attn",
      "runtime_subprocess": "model.layers.22.self_attn",
      "module_split_covered": true,
      "tensor_dataflow_covered": true,
      "stage_evidence": [],
      "input_tensor_ids": [
        "t00000057"
      ],
      "output_tensor_ids": [
        "t00001823"
      ]
    },
    {
      "event_detail_id": "input1_layer22/self_attn/call0255/op0045",
      "event_op_index": 64,
      "global_op_index": 1784,
      "op_name": "sub.Tensor",
      "op_schema": "aten::sub.Tensor(Tensor self, Tensor other, *, Scalar alpha=1) -> Tensor",
      "module_path": "model.layers.22.self_attn",
      "module_relative_path": "self_attn",
      "runtime_subprocess": "model.layers.22.self_attn",
      "module_split_covered": true,
      "tensor_dataflow_covered": true,
      "stage_evidence": [
        "visipruner_similarity_check"
      ],
      "input_tensor_ids": [
        "t00001822",
        "t00001823"
      ],
      "output_tensor_ids": [
        "t00001824"
      ]
    },
    {
      "event_detail_id": "input1_layer22/self_attn/call0255/op0046",
      "event_op_index": 65,
      "global_op_index": 1785,
      "op_name": "add.Tensor",
      "op_schema": "aten::add.Tensor(Tensor self, Tensor other, *, Scalar alpha=1) -> Tensor",
      "module_path": "model.layers.22.self_attn",
      "module_relative_path": "self_attn",
      "runtime_subprocess": "model.layers.22.self_attn",
      "module_split_covered": true,
      "tensor_dataflow_covered": true,
      "stage_evidence": [],
      "input_tensor_ids": [
        "t00001824"
      ],
      "output_tensor_ids": [
        "t00001825"
      ]
    },
    {
      "event_detail_id": "input1_layer22/self_attn/call0255/op0047",
      "event_op_index": 66,
      "global_op_index": 1786,
      "op_name": "eq.Scalar",
      "op_schema": "aten::eq.Scalar(Tensor self, Scalar other) -> Tensor",
      "module_path": "model.layers.22.self_attn",
      "module_relative_path": "self_attn",
      "runtime_subprocess": "model.layers.22.self_attn",
      "module_split_covered": true,
      "tensor_dataflow_covered": true,
      "stage_evidence": [],
      "input_tensor_ids": [
        "t00001825"
      ],
      "output_tensor_ids": [
        "t00001826"
      ]
    },
    {
      "event_detail_id": "input1_layer22/self_attn/call0255/op0048",
      "event_op_index": 67,
      "global_op_index": 1787,
      "op_name": "is_nonzero.default",
      "op_schema": "aten::is_nonzero(Tensor self) -> bool",
      "module_path": "model.layers.22.self_attn",
      "module_relative_path": "self_attn",
      "runtime_subprocess": "model.layers.22.self_attn",
      "module_split_covered": true,
      "tensor_dataflow_covered": true,
      "stage_evidence": [
        "visipruner_similarity_check"
      ],
      "input_tensor_ids": [
        "t00001826"
      ],
      "output_tensor_ids": []
    },
    {
      "event_detail_id": "input1_layer22/self_attn/call0255/op0049",
      "event_op_index": 68,
      "global_op_index": 1788,
      "op_name": "select.int",
      "op_schema": "aten::select.int(Tensor(a) self, int dim, SymInt index) -> Tensor(a)",
      "module_path": "model.layers.22.self_attn",
      "module_relative_path": "self_attn",
      "runtime_subprocess": "model.layers.22.self_attn",
      "module_split_covered": true,
      "tensor_dataflow_covered": true,
      "stage_evidence": [],
      "input_tensor_ids": [
        "t00001818"
      ],
      "output_tensor_ids": [
        "t00001827"
      ]
    },
    {
      "event_detail_id": "input1_layer22/self_attn/call0255/op0050",
      "event_op_index": 69,
      "global_op_index": 1789,
      "op_name": "select.int",
      "op_schema": "aten::select.int(Tensor(a) self, int dim, SymInt index) -> Tensor(a)",
      "module_path": "model.layers.22.self_attn",
      "module_relative_path": "self_attn",
      "runtime_subprocess": "model.layers.22.self_attn",
      "module_split_covered": true,
      "tensor_dataflow_covered": true,
      "stage_evidence": [],
      "input_tensor_ids": [
        "t00001814"
      ],
      "output_tensor_ids": [
        "t00001828"
      ]
    },
    {
      "event_detail_id": "input1_layer22/self_attn/call0255/op0051",
      "event_op_index": 70,
      "global_op_index": 1790,
      "op_name": "unsqueeze.default",
      "op_schema": "aten::unsqueeze(Tensor(a) self, int dim) -> Tensor(a)",
      "module_path": "model.layers.22.self_attn",
      "module_relative_path": "self_attn",
      "runtime_subprocess": "model.layers.22.self_attn",
      "module_split_covered": true,
      "tensor_dataflow_covered": true,
      "stage_evidence": [],
      "input_tensor_ids": [
        "t00001828"
      ],
      "output_tensor_ids": [
        "t00001829"
      ]
    },
    {
      "event_detail_id": "input1_layer22/self_attn/call0255/op0052",
      "event_op_index": 71,
      "global_op_index": 1791,
      "op_name": "mul.Tensor",
      "op_schema": "aten::mul.Tensor(Tensor self, Tensor other) -> Tensor",
      "module_path": "model.layers.22.self_attn",
      "module_relative_path": "self_attn",
      "runtime_subprocess": "model.layers.22.self_attn",
      "module_split_covered": true,
      "tensor_dataflow_covered": true,
      "stage_evidence": [],
      "input_tensor_ids": [
        "t00001829",
        "t00001782"
      ],
      "output_tensor_ids": [
        "t00001830"
      ]
    },
    {
      "event_detail_id": "input1_layer22/self_attn/call0255/op0053",
      "event_op_index": 72,
      "global_op_index": 1792,
      "op_name": "permute.default",
      "op_schema": "aten::permute(Tensor(a) self, int[] dims) -> Tensor(a)",
      "module_path": "model.layers.22.self_attn",
      "module_relative_path": "self_attn",
      "runtime_subprocess": "model.layers.22.self_attn",
      "module_split_covered": true,
      "tensor_dataflow_covered": true,
      "stage_evidence": [],
      "input_tensor_ids": [
        "t00001830"
      ],
      "output_tensor_ids": [
        "t00001831"
      ]
    },
    {
      "event_detail_id": "input1_layer22/self_attn/call0255/op0054",
      "event_op_index": 73,
      "global_op_index": 1793,
      "op_name": "contiguous.default",
      "op_schema": "aten::contiguous(Tensor(a) self, *, MemoryFormat memory_format=0) -> Tensor(a)",
      "module_path": "model.layers.22.self_attn",
      "module_relative_path": "self_attn",
      "runtime_subprocess": "model.layers.22.self_attn",
      "module_split_covered": true,
      "tensor_dataflow_covered": true,
      "stage_evidence": [
        "attention_output"
      ],
      "input_tensor_ids": [
        "t00001831"
      ],
      "output_tensor_ids": [
        "t00001832"
      ]
    },
    {
      "event_detail_id": "input1_layer22/self_attn/call0255/op0055",
      "event_op_index": 74,
      "global_op_index": 1794,
      "op_name": "view.default",
      "op_schema": "aten::view(Tensor(a) self, SymInt[] size) -> Tensor(a)",
      "module_path": "model.layers.22.self_attn",
      "module_relative_path": "self_attn",
      "runtime_subprocess": "model.layers.22.self_attn",
      "module_split_covered": true,
      "tensor_dataflow_covered": true,
      "stage_evidence": [],
      "input_tensor_ids": [
        "t00001832"
      ],
      "output_tensor_ids": [
        "t00001833"
      ]
    },
    {
      "event_detail_id": "input1_layer22/self_attn/call0255/op0056",
      "event_op_index": 75,
      "global_op_index": 1795,
      "op_name": "arange.start",
      "op_schema": "aten::arange.start(Scalar start, Scalar end, *, ScalarType? dtype=None, Layout? layout=None, Device? device=None, bool? pin_memory=None) -> Tensor",
      "module_path": "model.layers.22.self_attn",
      "module_relative_path": "self_attn",
      "runtime_subprocess": "model.layers.22.self_attn",
      "module_split_covered": true,
      "tensor_dataflow_covered": true,
      "stage_evidence": [
        "visipruner_similarity_check"
      ],
      "input_tensor_ids": [],
      "output_tensor_ids": [
        "t00001834"
      ]
    },
    {
      "event_detail_id": "input1_layer22/self_attn/call0255/op0057",
      "event_op_index": 76,
      "global_op_index": 1796,
      "op_name": "index.Tensor",
      "op_schema": "aten::index.Tensor(Tensor self, Tensor?[] indices) -> Tensor",
      "module_path": "model.layers.22.self_attn",
      "module_relative_path": "self_attn",
      "runtime_subprocess": "model.layers.22.self_attn",
      "module_split_covered": true,
      "tensor_dataflow_covered": true,
      "stage_evidence": [],
      "input_tensor_ids": [
        "t00001833",
        "t00001834"
      ],
      "output_tensor_ids": [
        "t00001835"
      ]
    },
    {
      "event_detail_id": "input1_layer22/self_attn/call0255/op0058",
      "event_op_index": 77,
      "global_op_index": 1797,
      "op_name": "unsqueeze.default",
      "op_schema": "aten::unsqueeze(Tensor(a) self, int dim) -> Tensor(a)",
      "module_path": "model.layers.22.self_attn",
      "module_relative_path": "self_attn",
      "runtime_subprocess": "model.layers.22.self_attn",
      "module_split_covered": true,
      "tensor_dataflow_covered": true,
      "stage_evidence": [],
      "input_tensor_ids": [
        "t00001827"
      ],
      "output_tensor_ids": [
        "t00001836"
      ]
    },
    {
      "event_detail_id": "input1_layer22/self_attn/call0255/op0059",
      "event_op_index": 78,
      "global_op_index": 1798,
      "op_name": "sub.Tensor",
      "op_schema": "aten::sub.Tensor(Tensor self, Tensor other, *, Scalar alpha=1) -> Tensor",
      "module_path": "model.layers.22.self_attn",
      "module_relative_path": "self_attn",
      "runtime_subprocess": "model.layers.22.self_attn",
      "module_split_covered": true,
      "tensor_dataflow_covered": true,
      "stage_evidence": [
        "visipruner_similarity_check"
      ],
      "input_tensor_ids": [
        "t00001836",
        "t00001835"
      ],
      "output_tensor_ids": [
        "t00001837"
      ]
    },
    {
      "event_detail_id": "input1_layer22/self_attn/call0255/op0060",
      "event_op_index": 79,
      "global_op_index": 1799,
      "op_name": "unsqueeze.default",
      "op_schema": "aten::unsqueeze(Tensor(a) self, int dim) -> Tensor(a)",
      "module_path": "model.layers.22.self_attn",
      "module_relative_path": "self_attn",
      "runtime_subprocess": "model.layers.22.self_attn",
      "module_split_covered": true,
      "tensor_dataflow_covered": true,
      "stage_evidence": [],
      "input_tensor_ids": [
        "t00001827"
      ],
      "output_tensor_ids": [
        "t00001838"
      ]
    },
    {
      "event_detail_id": "input1_layer22/self_attn/call0255/op0061",
      "event_op_index": 80,
      "global_op_index": 1800,
      "op_name": "cosine_similarity.default",
      "op_schema": "aten::cosine_similarity(Tensor x1, Tensor x2, int dim=1, float eps=1e-08) -> Tensor",
      "module_path": "model.layers.22.self_attn",
      "module_relative_path": "self_attn",
      "runtime_subprocess": "model.layers.22.self_attn",
      "module_split_covered": true,
      "tensor_dataflow_covered": true,
      "stage_evidence": [
        "visipruner_similarity_check"
      ],
      "input_tensor_ids": [
        "t00001837",
        "t00001838"
      ],
      "output_tensor_ids": [
        "t00001839"
      ]
    },
    {
      "event_detail_id": "input1_layer22/self_attn/call0255/op0062",
      "event_op_index": 81,
      "global_op_index": 1801,
      "op_name": "squeeze.dim",
      "op_schema": "aten::squeeze.dim(Tensor(a) self, int dim) -> Tensor(a)",
      "module_path": "model.layers.22.self_attn",
      "module_relative_path": "self_attn",
      "runtime_subprocess": "model.layers.22.self_attn",
      "module_split_covered": true,
      "tensor_dataflow_covered": true,
      "stage_evidence": [],
      "input_tensor_ids": [
        "t00001839"
      ],
      "output_tensor_ids": [
        "t00001840"
      ]
    },
    {
      "event_detail_id": "input1_layer22/self_attn/call0255/op0063",
      "event_op_index": 82,
      "global_op_index": 1802,
      "op_name": "lt.Scalar",
      "op_schema": "aten::lt.Scalar(Tensor self, Scalar other) -> Tensor",
      "module_path": "model.layers.22.self_attn",
      "module_relative_path": "self_attn",
      "runtime_subprocess": "model.layers.22.self_attn",
      "module_split_covered": true,
      "tensor_dataflow_covered": true,
      "stage_evidence": [],
      "input_tensor_ids": [
        "t00001840"
      ],
      "output_tensor_ids": [
        "t00001841"
      ]
    },
    {
      "event_detail_id": "input1_layer22/self_attn/call0255/op0064",
      "event_op_index": 83,
      "global_op_index": 1803,
      "op_name": "any.default",
      "op_schema": "aten::any(Tensor self) -> Tensor",
      "module_path": "model.layers.22.self_attn",
      "module_relative_path": "self_attn",
      "runtime_subprocess": "model.layers.22.self_attn",
      "module_split_covered": true,
      "tensor_dataflow_covered": true,
      "stage_evidence": [
        "visipruner_similarity_check"
      ],
      "input_tensor_ids": [
        "t00001841"
      ],
      "output_tensor_ids": [
        "t00001842"
      ]
    },
    {
      "event_detail_id": "input1_layer22/self_attn/call0255/op0065",
      "event_op_index": 84,
      "global_op_index": 1804,
      "op_name": "item.default",
      "op_schema": "aten::item(Tensor self) -> Scalar",
      "module_path": "model.layers.22.self_attn",
      "module_relative_path": "self_attn",
      "runtime_subprocess": "model.layers.22.self_attn",
      "module_split_covered": true,
      "tensor_dataflow_covered": true,
      "stage_evidence": [],
      "input_tensor_ids": [
        "t00001842"
      ],
      "output_tensor_ids": []
    },
    {
      "event_detail_id": "input1_layer22/self_attn/o_proj/call0260/op0001",
      "event_op_index": 85,
      "global_op_index": 1805,
      "op_name": "linear.default",
      "op_schema": "aten::linear(Tensor input, Tensor weight, Tensor? bias=None) -> Tensor",
      "module_path": "model.layers.22.self_attn.o_proj",
      "module_relative_path": "self_attn.o_proj",
      "runtime_subprocess": "model.layers.22.self_attn.o_proj",
      "module_split_covered": true,
      "tensor_dataflow_covered": true,
      "stage_evidence": [
        "attention_output",
        "mlp"
      ],
      "input_tensor_ids": [
        "t00001818",
        "t00001843"
      ],
      "output_tensor_ids": [
        "t00001844"
      ]
    },
    {
      "event_detail_id": "input1_layer22/model/layers/22/call0253/op0001",
      "event_op_index": 86,
      "global_op_index": 1806,
      "op_name": "add.Tensor",
      "op_schema": "aten::add.Tensor(Tensor self, Tensor other, *, Scalar alpha=1) -> Tensor",
      "module_path": "model.layers.22",
      "module_relative_path": "",
      "runtime_subprocess": "model.layers.22",
      "module_split_covered": true,
      "tensor_dataflow_covered": true,
      "stage_evidence": [
        "attention_output",
        "mlp"
      ],
      "input_tensor_ids": [
        "t00001761",
        "t00001844"
      ],
      "output_tensor_ids": [
        "t00001845"
      ]
    },
    {
      "event_detail_id": "input1_layer22/post_attention_layernorm/call0261/op0001",
      "event_op_index": 87,
      "global_op_index": 1807,
      "op_name": "to.dtype",
      "op_schema": "aten::to.dtype(Tensor(a) self, ScalarType dtype, bool non_blocking=False, bool copy=False, MemoryFormat? memory_format=None) -> Tensor(a)",
      "module_path": "model.layers.22.post_attention_layernorm",
      "module_relative_path": "post_attention_layernorm",
      "runtime_subprocess": "model.layers.22.post_attention_layernorm",
      "module_split_covered": true,
      "tensor_dataflow_covered": true,
      "stage_evidence": [
        "mlp"
      ],
      "input_tensor_ids": [
        "t00001845"
      ],
      "output_tensor_ids": [
        "t00001846"
      ]
    },
    {
      "event_detail_id": "input1_layer22/post_attention_layernorm/call0261/op0002",
      "event_op_index": 88,
      "global_op_index": 1808,
      "op_name": "pow.Tensor_Scalar",
      "op_schema": "aten::pow.Tensor_Scalar(Tensor self, Scalar exponent) -> Tensor",
      "module_path": "model.layers.22.post_attention_layernorm",
      "module_relative_path": "post_attention_layernorm",
      "runtime_subprocess": "model.layers.22.post_attention_layernorm",
      "module_split_covered": true,
      "tensor_dataflow_covered": true,
      "stage_evidence": [
        "mlp"
      ],
      "input_tensor_ids": [
        "t00001846"
      ],
      "output_tensor_ids": [
        "t00001847"
      ]
    },
    {
      "event_detail_id": "input1_layer22/post_attention_layernorm/call0261/op0003",
      "event_op_index": 89,
      "global_op_index": 1809,
      "op_name": "mean.dim",
      "op_schema": "aten::mean.dim(Tensor self, int[1]? dim, bool keepdim=False, *, ScalarType? dtype=None) -> Tensor",
      "module_path": "model.layers.22.post_attention_layernorm",
      "module_relative_path": "post_attention_layernorm",
      "runtime_subprocess": "model.layers.22.post_attention_layernorm",
      "module_split_covered": true,
      "tensor_dataflow_covered": true,
      "stage_evidence": [
        "mlp"
      ],
      "input_tensor_ids": [
        "t00001847"
      ],
      "output_tensor_ids": [
        "t00001848"
      ]
    },
    {
      "event_detail_id": "input1_layer22/post_attention_layernorm/call0261/op0004",
      "event_op_index": 90,
      "global_op_index": 1810,
      "op_name": "add.Tensor",
      "op_schema": "aten::add.Tensor(Tensor self, Tensor other, *, Scalar alpha=1) -> Tensor",
      "module_path": "model.layers.22.post_attention_layernorm",
      "module_relative_path": "post_attention_layernorm",
      "runtime_subprocess": "model.layers.22.post_attention_layernorm",
      "module_split_covered": true,
      "tensor_dataflow_covered": true,
      "stage_evidence": [
        "mlp"
      ],
      "input_tensor_ids": [
        "t00001848"
      ],
      "output_tensor_ids": [
        "t00001849"
      ]
    },
    {
      "event_detail_id": "input1_layer22/post_attention_layernorm/call0261/op0005",
      "event_op_index": 91,
      "global_op_index": 1811,
      "op_name": "rsqrt.default",
      "op_schema": "aten::rsqrt(Tensor self) -> Tensor",
      "module_path": "model.layers.22.post_attention_layernorm",
      "module_relative_path": "post_attention_layernorm",
      "runtime_subprocess": "model.layers.22.post_attention_layernorm",
      "module_split_covered": true,
      "tensor_dataflow_covered": true,
      "stage_evidence": [
        "mlp"
      ],
      "input_tensor_ids": [
        "t00001849"
      ],
      "output_tensor_ids": [
        "t00001850"
      ]
    },
    {
      "event_detail_id": "input1_layer22/post_attention_layernorm/call0261/op0006",
      "event_op_index": 92,
      "global_op_index": 1812,
      "op_name": "mul.Tensor",
      "op_schema": "aten::mul.Tensor(Tensor self, Tensor other) -> Tensor",
      "module_path": "model.layers.22.post_attention_layernorm",
      "module_relative_path": "post_attention_layernorm",
      "runtime_subprocess": "model.layers.22.post_attention_layernorm",
      "module_split_covered": true,
      "tensor_dataflow_covered": true,
      "stage_evidence": [
        "mlp"
      ],
      "input_tensor_ids": [
        "t00001846",
        "t00001850"
      ],
      "output_tensor_ids": [
        "t00001851"
      ]
    },
    {
      "event_detail_id": "input1_layer22/post_attention_layernorm/call0261/op0007",
      "event_op_index": 93,
      "global_op_index": 1813,
      "op_name": "to.dtype",
      "op_schema": "aten::to.dtype(Tensor(a) self, ScalarType dtype, bool non_blocking=False, bool copy=False, MemoryFormat? memory_format=None) -> Tensor(a)",
      "module_path": "model.layers.22.post_attention_layernorm",
      "module_relative_path": "post_attention_layernorm",
      "runtime_subprocess": "model.layers.22.post_attention_layernorm",
      "module_split_covered": true,
      "tensor_dataflow_covered": true,
      "stage_evidence": [
        "mlp"
      ],
      "input_tensor_ids": [
        "t00001851"
      ],
      "output_tensor_ids": [
        "t00001852"
      ]
    },
    {
      "event_detail_id": "input1_layer22/post_attention_layernorm/call0261/op0008",
      "event_op_index": 94,
      "global_op_index": 1814,
      "op_name": "mul.Tensor",
      "op_schema": "aten::mul.Tensor(Tensor self, Tensor other) -> Tensor",
      "module_path": "model.layers.22.post_attention_layernorm",
      "module_relative_path": "post_attention_layernorm",
      "runtime_subprocess": "model.layers.22.post_attention_layernorm",
      "module_split_covered": true,
      "tensor_dataflow_covered": true,
      "stage_evidence": [
        "mlp"
      ],
      "input_tensor_ids": [
        "t00001853",
        "t00001852"
      ],
      "output_tensor_ids": [
        "t00001854"
      ]
    },
    {
      "event_detail_id": "input1_layer22/mlp/gate_proj/call0263/op0001",
      "event_op_index": 95,
      "global_op_index": 1815,
      "op_name": "linear.default",
      "op_schema": "aten::linear(Tensor input, Tensor weight, Tensor? bias=None) -> Tensor",
      "module_path": "model.layers.22.mlp.gate_proj",
      "module_relative_path": "mlp.gate_proj",
      "runtime_subprocess": "model.layers.22.mlp.gate_proj",
      "module_split_covered": true,
      "tensor_dataflow_covered": true,
      "stage_evidence": [
        "mlp"
      ],
      "input_tensor_ids": [
        "t00001854",
        "t00001855"
      ],
      "output_tensor_ids": [
        "t00001856"
      ]
    },
    {
      "event_detail_id": "input1_layer22/mlp/act_fn/call0264/op0001",
      "event_op_index": 96,
      "global_op_index": 1816,
      "op_name": "silu.default",
      "op_schema": "aten::silu(Tensor self) -> Tensor",
      "module_path": "model.layers.22.mlp.act_fn",
      "module_relative_path": "mlp.act_fn",
      "runtime_subprocess": "model.layers.22.mlp.act_fn",
      "module_split_covered": true,
      "tensor_dataflow_covered": true,
      "stage_evidence": [
        "mlp"
      ],
      "input_tensor_ids": [
        "t00001856"
      ],
      "output_tensor_ids": [
        "t00001857"
      ]
    },
    {
      "event_detail_id": "input1_layer22/mlp/up_proj/call0265/op0001",
      "event_op_index": 97,
      "global_op_index": 1817,
      "op_name": "linear.default",
      "op_schema": "aten::linear(Tensor input, Tensor weight, Tensor? bias=None) -> Tensor",
      "module_path": "model.layers.22.mlp.up_proj",
      "module_relative_path": "mlp.up_proj",
      "runtime_subprocess": "model.layers.22.mlp.up_proj",
      "module_split_covered": true,
      "tensor_dataflow_covered": true,
      "stage_evidence": [
        "mlp"
      ],
      "input_tensor_ids": [
        "t00001854",
        "t00001858"
      ],
      "output_tensor_ids": [
        "t00001859"
      ]
    },
    {
      "event_detail_id": "input1_layer22/mlp/call0262/op0001",
      "event_op_index": 98,
      "global_op_index": 1818,
      "op_name": "mul.Tensor",
      "op_schema": "aten::mul.Tensor(Tensor self, Tensor other) -> Tensor",
      "module_path": "model.layers.22.mlp",
      "module_relative_path": "mlp",
      "runtime_subprocess": "model.layers.22.mlp",
      "module_split_covered": true,
      "tensor_dataflow_covered": true,
      "stage_evidence": [
        "mlp"
      ],
      "input_tensor_ids": [
        "t00001857",
        "t00001859"
      ],
      "output_tensor_ids": [
        "t00001860"
      ]
    },
    {
      "event_detail_id": "input1_layer22/mlp/down_proj/call0266/op0001",
      "event_op_index": 99,
      "global_op_index": 1819,
      "op_name": "linear.default",
      "op_schema": "aten::linear(Tensor input, Tensor weight, Tensor? bias=None) -> Tensor",
      "module_path": "model.layers.22.mlp.down_proj",
      "module_relative_path": "mlp.down_proj",
      "runtime_subprocess": "model.layers.22.mlp.down_proj",
      "module_split_covered": true,
      "tensor_dataflow_covered": true,
      "stage_evidence": [
        "attention_output"
      ],
      "input_tensor_ids": [
        "t00001860",
        "t00001861"
      ],
      "output_tensor_ids": [
        "t00001862"
      ]
    },
    {
      "event_detail_id": "input1_layer22/model/layers/22/call0253/op0002",
      "event_op_index": 100,
      "global_op_index": 1820,
      "op_name": "add.Tensor",
      "op_schema": "aten::add.Tensor(Tensor self, Tensor other, *, Scalar alpha=1) -> Tensor",
      "module_path": "model.layers.22",
      "module_relative_path": "",
      "runtime_subprocess": "model.layers.22",
      "module_split_covered": true,
      "tensor_dataflow_covered": true,
      "stage_evidence": [
        "attention_output"
      ],
      "input_tensor_ids": [
        "t00001845",
        "t00001862"
      ],
      "output_tensor_ids": [
        "t00001863"
      ]
    }
  ]
}
